pytilkit/__init__.py
pytilkit/clearScreen.py
pytilkit/crypted.py
pytilkit/jsoned.py
pytilkit/maths.py
pytilkit/sized.py
pytilkit-1.0.1.dist-info/LICENSE
pytilkit-1.0.1.dist-info/METADATA
pytilkit-1.0.1.dist-info/WHEEL
pytilkit-1.0.1.dist-info/top_level.txt
pytilkit-1.0.1.dist-info/RECORD
