Metadata-Version: 2.1
Name: pytilkit
Version: 1.0.1
Summary: A utility package for various functionalities including math operations, JSON handling, and RSA encryption
Home-page: https://github.com/yourusername/pyutilkit
Author: Srijal Dutta
Author-email: srijaldutta.official+pytilkit@gmail.com
License: UNKNOWN
Platform: UNKNOWN
Classifier: Programming Language :: Python :: 3
Classifier: Operating System :: OS Independent
Requires-Python: >=3.6
Requires-Dist: cryptography
